certainty_tensorflow/__init__.py
certainty_tensorflow-0.0.1.dist-info/LICENSE.txt
certainty_tensorflow-0.0.1.dist-info/METADATA
certainty_tensorflow-0.0.1.dist-info/WHEEL
certainty_tensorflow-0.0.1.dist-info/top_level.txt
certainty_tensorflow-0.0.1.dist-info/RECORD
