Metadata-Version: 2.1
Name: certainty-tensorflow
Version: 0.0.1
Summary: P r o b a b l i s t i c   m o d e l s   o f   c e r t a i n t y   i n   T e n s o r f l o w .
Home-page: https://github.com/prijatelj/certainty-tensorflow
Author: Derek S. Prijatelj
Author-email: dprijate@nd.edu
License: UNKNOWN
Platform: UNKNOWN
Classifier: Programming Language :: Python :: 3
Classifier: License :: OSI Approved :: MIT License
Classifier: Operating System :: OS Independent
Requires-Python: >=3.8
License-File: LICENSE.txt
